odoo/addons/partner_usps_address_validation/README.rst
odoo/addons/partner_usps_address_validation/__init__.py
odoo/addons/partner_usps_address_validation/__manifest__.py
odoo/addons/partner_usps_address_validation/requirements.txt
odoo/addons/partner_usps_address_validation/i18n/partner_usps_address_validation.pot
odoo/addons/partner_usps_address_validation/models/__init__.py
odoo/addons/partner_usps_address_validation/models/res_partner.py
odoo/addons/partner_usps_address_validation/models/usps_credential_configuration.py
odoo/addons/partner_usps_address_validation/readme/CONFIGURATION.rst
odoo/addons/partner_usps_address_validation/readme/CONTRIBUTORS.rst
odoo/addons/partner_usps_address_validation/readme/CREDITS.rst
odoo/addons/partner_usps_address_validation/readme/DESCRIPTION.rst
odoo/addons/partner_usps_address_validation/security/ir.model.access.csv
odoo/addons/partner_usps_address_validation/static/description/icon.png
odoo/addons/partner_usps_address_validation/static/description/index.html
odoo/addons/partner_usps_address_validation/views/config.xml
odoo/addons/partner_usps_address_validation/views/res_partner.xml
odoo/addons/partner_usps_address_validation/wizard/__init__.py
odoo/addons/partner_usps_address_validation/wizard/usps_address_validation.py
odoo/addons/partner_usps_address_validation/wizard/usps_address_validation.xml
odoo14_addon_partner_usps_address_validation-14.0.1.0.1.dev1.dist-info/METADATA
odoo14_addon_partner_usps_address_validation-14.0.1.0.1.dev1.dist-info/WHEEL
odoo14_addon_partner_usps_address_validation-14.0.1.0.1.dev1.dist-info/top_level.txt
odoo14_addon_partner_usps_address_validation-14.0.1.0.1.dev1.dist-info/RECORD
