Metadata-Version: 2.1
Name: odoo14-addon-partner_usps_address_validation
Version: 14.0.1.0.1.dev1
Summary: Utilize the USPS open API for address validation
Home-page: https://github.com/OCA/l10n-usa
Author: Open Source Integrators, Odoo Community Association (OCA)
Author-email: support@odoo-community.org
License: AGPL-3
Classifier: Programming Language :: Python
Classifier: Framework :: Odoo
Classifier: Framework :: Odoo :: 14.0
Classifier: License :: OSI Approved :: GNU Affero General Public License v3
Requires-Python: >=3.6
Requires-Dist: odoo<14.1dev,>=14.0a
Requires-Dist: requests
Requires-Dist: xmltodict
